model_hallucination/__init__.py
model_hallucination/cli.py
model_hallucination/dataset_loader.py
model_hallucination/evaluator.py
tests/__init__.py
tests/test_cli.py
model_hallucination_cli-1.0.0.dist-info/METADATA
model_hallucination_cli-1.0.0.dist-info/WHEEL
model_hallucination_cli-1.0.0.dist-info/entry_points.txt
model_hallucination_cli-1.0.0.dist-info/top_level.txt
model_hallucination_cli-1.0.0.dist-info/RECORD
