Metadata-Version: 2.1
Name: model-hallucination-cli
Version: 1.0.0
Summary: A CLI for checking model hallucinations using Hugging Face datasets.
Home-page: https://github.com/abhijit/model-hallucination-cli
Author: Abhijit
Author-email: Abhijit <abhijitsr92@gmail.com>
Requires-Python: >=3.7
Requires-Dist: typer >=0.9.0
Requires-Dist: rich >=13.4.0
Requires-Dist: datasets >=2.14.0
Requires-Dist: numpy <1.22.0,>=1.21.0
